examples/__init__.py
snuba_sdk/__init__.py
snuba_sdk/aliased_expression.py
snuba_sdk/column.py
snuba_sdk/conditions.py
snuba_sdk/delete_query.py
snuba_sdk/entity.py
snuba_sdk/expressions.py
snuba_sdk/formula.py
snuba_sdk/function.py
snuba_sdk/legacy.py
snuba_sdk/metrics_query.py
snuba_sdk/metrics_query_visitors.py
snuba_sdk/metrics_visitors.py
snuba_sdk/mql_context.py
snuba_sdk/mql_visitor.py
snuba_sdk/orderby.py
snuba_sdk/py.typed
snuba_sdk/query.py
snuba_sdk/query_validation.py
snuba_sdk/query_visitors.py
snuba_sdk/relationships.py
snuba_sdk/request.py
snuba_sdk/schema.py
snuba_sdk/snuba.py
snuba_sdk/storage.py
snuba_sdk/timeseries.py
snuba_sdk/visitors.py
snuba_sdk/mql/__init__.py
snuba_sdk/mql/mql.py
snuba_sdk/query_optimizers/__init__.py
snuba_sdk/query_optimizers/or_optimizer.py
snuba_sdk-3.0.43.dist-info/LICENSE.md
snuba_sdk-3.0.43.dist-info/METADATA
snuba_sdk-3.0.43.dist-info/WHEEL
snuba_sdk-3.0.43.dist-info/top_level.txt
snuba_sdk-3.0.43.dist-info/RECORD
