Metadata-Version: 2.1
Name: snuba-sdk
Version: 3.0.43
Summary: Snuba SDK for generating SnQL queries.
Home-page: https://github.com/getsentry/snuba-sdk
Author: Sentry
Author-email: oss@sentry.io
License: FSL-1.0-Apache-2.0
Project-URL: Changelog, https://github.com/getsentry/snuba-sdk/blob/main/CHANGES.rst
Classifier: Development Status :: 5 - Production/Stable
Classifier: Environment :: Web Environment
Classifier: Intended Audience :: Developers
Classifier: License :: Other/Proprietary License
Classifier: Operating System :: OS Independent
Classifier: Programming Language :: Python
Classifier: Programming Language :: Python :: 3
Classifier: Programming Language :: Python :: 3.7
Classifier: Programming Language :: Python :: 3.8
Classifier: Programming Language :: Python :: 3.9
Classifier: Topic :: Software Development :: Libraries :: Python Modules
License-File: LICENSE.md
Requires-Dist: parsimonious>=0.10.0
